{
  "id": "event-2026-07-19-business-meeting",
  "title": "Quarterly Business Meeting",
  "date": "2026-07-19",
  "description": "We encourage your attendance this evening at the business meeting. We will be discussing church finances, vacation bible school and upcoming church projects and events! Your input and participation are greatly appreciated as we plan for the future of our church. We look forward to seeing everyone there.",
  "location": "Victory Baptist Church - 295 Pleasant View Drive, Kittanning, PA 16201",
  "category": "meeting"
}
